folium/__init__.py
folium/elements.py
folium/features.py
folium/folium.py
folium/map.py
folium/raster_layers.py
folium/utilities.py
folium/vector_layers.py
folium/plugins/__init__.py
folium/plugins/antpath.py
folium/plugins/beautify_icon.py
folium/plugins/boat_marker.py
folium/plugins/draw.py
folium/plugins/dual_map.py
folium/plugins/fast_marker_cluster.py
folium/plugins/feature_group_sub_group.py
folium/plugins/float_image.py
folium/plugins/fullscreen.py
folium/plugins/geocoder.py
folium/plugins/heat_map.py
folium/plugins/heat_map_withtime.py
folium/plugins/locate_control.py
folium/plugins/marker_cluster.py
folium/plugins/measure_control.py
folium/plugins/minimap.py
folium/plugins/mouse_position.py
folium/plugins/pattern.py
folium/plugins/polyline_offset.py
folium/plugins/polyline_text_path.py
folium/plugins/scroll_zoom_toggler.py
folium/plugins/search.py
folium/plugins/semicircle.py
folium/plugins/terminator.py
folium/plugins/time_slider_choropleth.py
folium/plugins/timestamped_geo_json.py
folium/plugins/timestamped_wmstilelayer.py
folium/plugins/vectorgrid_protobuf.py
folium/templates/fit_bounds.js
folium/templates/leaflet_heat.min.js
folium/templates/pa7_hm.min.js
folium/templates/pa7_leaflet_hm.min.js
folium/templates/tiles/amapchina/attr.txt
folium/templates/tiles/amapchina/tiles.txt
folium/templates/tiles/baidumapschina/attr.txt
folium/templates/tiles/baidumapschina/tiles.txt
folium/templates/tiles/cartodbdark_matter/attr.txt
folium/templates/tiles/cartodbdark_matter/tiles.txt
folium/templates/tiles/cartodbpositron/attr.txt
folium/templates/tiles/cartodbpositron/tiles.txt
folium/templates/tiles/cartodbpositronnolabels/attr.txt
folium/templates/tiles/cartodbpositronnolabels/tiles.txt
folium/templates/tiles/cartodbpositrononlylabels/attr.txt
folium/templates/tiles/cartodbpositrononlylabels/tiles.txt
folium/templates/tiles/geoqchinacommunity/attr.txt
folium/templates/tiles/geoqchinacommunity/tiles.txt
folium/templates/tiles/geoqchinastreet/attr.txt
foliume-0.0.1.dist-info/LICENSE.txt
foliume-0.0.1.dist-info/METADATA
foliume-0.0.1.dist-info/WHEEL
foliume-0.0.1.dist-info/top_level.txt
foliume-0.0.1.dist-info/RECORD
