Metadata-Version: 2.1
Name: foliume
Version: 0.0.1
Summary: Make beautiful maps with Leaflet.js & Python
Home-page: https://github.com/geoyee/folium
Author: Rob Story
Author-email: wrobstory@gmail.com
License: MIT
Keywords: data visualization
Platform: any
Classifier: Programming Language :: Python :: 3.5
Classifier: Programming Language :: Python :: 3.6
Classifier: Programming Language :: Python :: 3.7
Classifier: Topic :: Scientific/Engineering :: GIS
Classifier: Topic :: Scientific/Engineering :: Visualization
Classifier: License :: OSI Approved :: MIT License
Classifier: Development Status :: 5 - Production/Stable
Requires-Python: >=3.5
Provides-Extra: testing
License-File: LICENSE.txt
